show_dt/__init__.py
show_dt/show.py
show_dt/supertree/__init__.py
show_dt/supertree/model_loader.py
show_dt/supertree/node.py
show_dt/supertree/supertree.py
show_dt/supertree/templatehtml.py
show_dt/supertree/treedata.py
show_dt-0.0.2.dist-info/METADATA
show_dt-0.0.2.dist-info/WHEEL
show_dt-0.0.2.dist-info/top_level.txt
show_dt-0.0.2.dist-info/RECORD
