Metadata-Version: 2.1
Name: show-dt
Version: 0.0.2
Summary: show decisiontree
Author: MAPS
Author-email: dongguk.maps@gmail.com
Keywords: Decision Tree,DT
Classifier: Programming Language :: Python :: 3.7
Classifier: Programming Language :: Python :: 3.8
Classifier: Programming Language :: Python :: 3.9
Requires-Python: >=3.7
